selvage/__main__.py
selvage/__version__.py
selvage/cli.py
selvage/resources/error_patterns.yml
selvage/resources/models.yml
selvage/resources/prompt/synthesis/recommendation_synthesis_prompt.txt
selvage/resources/prompt/synthesis/summary_synthesis_prompt.txt
selvage/resources/prompt/synthesis/synthesis_system_prompt.txt
selvage/resources/prompt/v1/code_review_system_prompt_v1.txt
selvage/resources/prompt/v1/deepeval_result_file_conversion_prompt_v1.md
selvage/resources/prompt/v2/code_review_system_prompt_v2.txt
selvage/resources/prompt/v3/code_review_system_prompt_v3.txt
selvage/resources/prompt/v4/code_review_system_prompt_v4.txt
selvage/src/__init__.py
selvage/src/config.py
selvage/src/model_config.py
selvage/src/ui.py
selvage/src/cache/__init__.py
selvage/src/cache/cache_key_generator.py
selvage/src/cache/cache_manager.py
selvage/src/cache/models.py
selvage/src/context_extractor/__init__.py
selvage/src/context_extractor/context_extractor.py
selvage/src/context_extractor/fallback_context_extractor.py
selvage/src/context_extractor/line_range.py
selvage/src/context_extractor/meaningless_change_filter.py
selvage/src/diff_parser/__init__.py
selvage/src/diff_parser/constants.py
selvage/src/diff_parser/parser.py
selvage/src/diff_parser/models/__init__.py
selvage/src/diff_parser/models/diff_result.py
selvage/src/diff_parser/models/file_diff.py
selvage/src/diff_parser/models/hunk.py
selvage/src/diff_parser/utils/__init__.py
selvage/src/diff_parser/utils/hunk_line_calculator.py
selvage/src/exceptions/__init__.py
selvage/src/exceptions/api_key_not_found_error.py
selvage/src/exceptions/context_extraction_error.py
selvage/src/exceptions/context_limit_exceeded_error.py
selvage/src/exceptions/diff_parsing_error.py
selvage/src/exceptions/invalid_api_key_error.py
selvage/src/exceptions/invalid_model_provider_error.py
selvage/src/exceptions/json_parsing_error.py
selvage/src/exceptions/llm_gateway_error.py
selvage/src/exceptions/openrouter_api_error.py
selvage-0.2.0.dist-info/licenses/LICENSE
selvage-0.2.0.dist-info/licenses/NOTICE
selvage-0.2.0.dist-info/METADATA
selvage-0.2.0.dist-info/WHEEL
selvage-0.2.0.dist-info/entry_points.txt
selvage-0.2.0.dist-info/top_level.txt
selvage-0.2.0.dist-info/RECORD
