Metadata-Version: 2.4
Name: selvage
Version: 0.2.0
Summary: LLM 기반 코드 리뷰 도구
Author: Selvage Team
License: Apache-2.0
Project-URL: Homepage, https://selvage.me
Project-URL: Repository, https://github.com/selvage-lab/selvage/
Project-URL: Documentation, https://github.com/selvage-lab/selvage/#readme
Project-URL: Bug Tracker, https://github.com/selvage-lab/selvage//issues
Keywords: code-review,llm,ai,git,cli,python
Classifier: Development Status :: 4 - Beta
Classifier: Environment :: Console
Classifier: Intended Audience :: Developers
Classifier: Topic :: Software Development :: Quality Assurance
Classifier: Topic :: Software Development :: Version Control :: Git
Classifier: Programming Language :: Python :: 3
Classifier: Programming Language :: Python :: 3.10
Classifier: Programming Language :: Python :: 3.11
Classifier: Programming Language :: Python :: 3.12
Classifier: Programming Language :: Python :: 3.13
Classifier: License :: OSI Approved :: Apache Software License
Classifier: Operating System :: OS Independent
Requires-Python: >=3.10
License-File: LICENSE
License-File: NOTICE
Requires-Dist: requests==2.32.3
Requires-Dist: pydantic<3.0.0,>=2.11.7
Requires-Dist: openai<2.0.0,>=1.95.1
Requires-Dist: anthropic==0.49.0
Requires-Dist: tiktoken==0.9.0
Requires-Dist: streamlit==1.43.2
Requires-Dist: instructor==1.8.0
Requires-Dist: google-genai==1.13.0
Requires-Dist: click==8.1.8
Requires-Dist: PyYAML==6.0.1
Requires-Dist: rich<14.0.0,>=13.9.4
Requires-Dist: httpx==0.28.1
Requires-Dist: tree-sitter-language-pack==0.9.0
Requires-Dist: deprecated==1.2.15
Requires-Dist: tenacity<10.0.0,>=9.0.0
Requires-Dist: fastmcp>=2.12.0
Provides-Extra: dev
Requires-Dist: pytest==8.3.5; extra == "dev"
Requires-Dist: pytest-cov==4.1.0; extra == "dev"
Requires-Dist: pytest-asyncio>=0.23.0; extra == "dev"
Requires-Dist: build==1.0.3; extra == "dev"
Requires-Dist: twine==6.1.0; extra == "dev"
Requires-Dist: wheel==0.43.0; extra == "dev"
Requires-Dist: pre-commit==4.2.0; extra == "dev"
Provides-Extra: e2e
Requires-Dist: testcontainers>=4.0.0; extra == "e2e"
Requires-Dist: docker>=6.0.0; extra == "e2e"
Requires-Dist: pytest-xdist>=3.0.0; extra == "e2e"
Requires-Dist: pytest-timeout>=2.0.0; extra == "e2e"
Requires-Dist: pytest-mock>=3.10.0; extra == "e2e"
Requires-Dist: pytest-subprocess>=1.5.0; extra == "e2e"
Dynamic: license-file
